LICENSE.txt
MANIFEST.in
README.rst
setup.py
Zinc.egg-info/PKG-INFO
Zinc.egg-info/SOURCES.txt
Zinc.egg-info/dependency_links.txt
Zinc.egg-info/requires.txt
Zinc.egg-info/top_level.txt
examples/multi_process.py
examples/multiple_orders.json
examples/request_processor_example.py
examples/sample_information.json
examples/simple_order.json
examples/simple_order_example.py
examples/simple_order_use_default_example.py
zinc/__init__.py
zinc/__main__.py
zinc/format_price.py
zinc/shipping_method_factory.py
zinc/zinc_request_processor.py
zinc/zinc_simple_order.py
zinc/zinc_wizard.py