Metadata-Version: 1.0
Name: Zinc
Version: 0.1.17
Summary: Wrapper for Zinc ecommerce API (zinc.io)
Home-page: https://github.com/wangjohn/zinc_cli
Author: John Wang
Author-email: john@zinc.io
License: LICENSE.txt
Platform: UNKNOWN
